{"Weapons":[[null,null,null,null,null,null,null,null,null,null,{"sb_id":"NA","name":"§cFancy Sword","lore":["§cFancy Sword","§7Click on this item in your inventory to","§7add it to your §9Museum§7!","","§7Reward: §b+1 SkyBlock XP","","§7§eRight click to search this item on the","§eAuction House!"]},{"sb_id":"NA","name":"§cUndead Sword","lore":["§cUndead Sword","§7Click on this item in your inventory to","§7add it to your §9Museum§7!","","§7Donating a §9Revenant Falchion §7will","§7count as donating this item.","","§7Reward: §b+1 SkyBlock XP","","§7§eRight click to search this item on the","§eAuction House!"]},{"sb_id":"NA","name":"§cSpider Sword","lore":["§cSpider Sword","§7Click on this item in your inventory to","§7add it to your §9Museum§7!","","§7Donating a §9Recluse Fang §7will count","§7as donating this item.","","§7Reward: §b+1 SkyBlock XP","","§7§eRight click to search this item on the","§eAuction House!"]},{"sb_id":"NA","name":"§cRogue Sword","lore":["§cRogue Sword","§7Click on this item in your inventory to","§7add it to your §9Museum§7!","","§7Reward: §b+1 SkyBlock XP"]},{"sb_id":"ASPECT_OF_THE_JERRY","name":"§fAspect of the Jerry","lore":["§fAspect of the Jerry","§7Damage: §c+1","","§6Ability: Parley  §e§lRIGHT CLICK","§7Channel your inner Jerry.","§8Cooldown: §a5s","","§7§8This item can be reforged!","§8§l* §8Co-op Soulbound §8§l*","§f§lCOMMON SWORD","§8§m §8§m §8§m §8§m §8§m §8§m §8§m §8§m §8§m §8§m §8§m §8§m §8§m §8§m §8§m §8§m §8§m §8§m §8§m §8§m §8§m §8§m §8§m §8§m §8§m ","§7Donated: §bOct 28, 2024","§7Created: §aOct 06, 2019","§7Clean Value: §cUnknown","§7Reward: §b+1 SkyBlock XP §a✔","","§9Weapons Wing Slot #7","","§eClick to retrieve item!"]},{"sb_id":"CLEAVER","name":"§aCleaver","lore":["§aCleaver","§7Damage: §c+40","§7Strength: §c+10","","§6Ability: Cleave ","§7When hitting an entity, monsters in a","§7§a3§7 block range will be hit for a","§7portion of that damage too.","","§7§8This item can be reforged!","§8§l* §8Co-op Soulbound §8§l*","§a§lUNCOMMON SWORD","§8§m §8§m §8§m §8§m §8§m §8§m §8§m §8§m §8§m §8§m §8§m §8§m §8§m §8§m §8§m §8§m §8§m §8§m §8§m §8§m §8§m §8§m §8§m §8§m §8§m ","§7Donated: §bOct 28, 2024","§7Created: §aOct 28, 2024","§7Clean Value: §6500 Coins","§7Reward: §b+1 SkyBlock XP §a✔","","§9Atrium Slot #15","","§eClick to retrieve item!"]},{"sb_id":"END_SWORD","name":"§aEnd Sword","lore":["§aEnd Sword","§7Damage: §c+35","","§7Deals §a+100% §7damage to §7Endermites§7,","§7§7Endermen§7, and §7Ender Dragons§7.","","§7§8This item can be reforged!","§8§l* §8Co-op Soulbound §8§l*","§a§lUNCOMMON SWORD","§8§m §8§m §8§m §8§m §8§m §8§m §8§m §8§m §8§m §8§m §8§m §8§m §8§m §8§m §8§m §8§m §8§m §8§m §8§m §8§m §8§m §8§m §8§m §8§m §8§m ","§7Donated: §bOct 28, 2024","§7Created: §aOct 28, 2024","§7Clean Value: §61,150 Coins","§7Reward: §b+1 SkyBlock XP §a✔","","§9Weapons Wing Slot #1","","§eClick to retrieve item!"]},null,null,{"sb_id":"NA","name":"§cSquire Sword","lore":["§cSquire Sword","§7Click on this item in your inventory to","§7add it to your §9Museum§7!","","§7Reward: §b+1 SkyBlock XP","","§7§eRight click to search this item on the","§eAuction House!"]},{"sb_id":"NA","name":"§cCeleste Wand","lore":["§cCeleste Wand","§7Click on this item in your inventory to","§7add it to your §9Museum§7!","","§7Reward: §b+1 SkyBlock XP","","§7§eRight click to search this item on the","§eAuction House!"]},{"sb_id":"NA","name":"§cArtisanal Shortbow","lore":["§cArtisanal Shortbow","§7Click on this item in your inventory to","§7add it to your §9Museum§7!","","§7Reward: §b+1 SkyBlock XP","","§7§eRight click to search this item on the","§eAuction House!"]},{"sb_id":"NA","name":"§cPrismarine Bow","lore":["§cPrismarine Bow","§7Click on this item in your inventory to","§7add it to your §9Museum§7!","","§7Reward: §b+2 SkyBlock XP","","§7§eRight click to search this item on the","§eAuction House!"]},{"sb_id":"WITHER_BOW","name":"§aWither Bow","lore":["§aWither Bow","§7Damage: §c+30","","§7Deals §a+100% §7damage to §aWithers §7and","§7§aWither Skeletons§7.","","§7§8This item can be reforged!","§8§l* §8Co-op Soulbound §8§l*","§a§lUNCOMMON BOW","§8§m §8§m §8§m §8§m §8§m §8§m §8§m §8§m §8§m §8§m §8§m §8§m §8§m §8§m §8§m §8§m §8§m §8§m §8§m §8§m §8§m §8§m §8§m §8§m §8§m ","§7Donated: §bOct 28, 2024","§7Created: §aOct 25, 2024","§7Clean Value: §6290 Coins","§7Reward: §b+2 SkyBlock XP §a✔","","§9Atrium Slot #16","","§eClick to retrieve item!"]},{"sb_id":"NA","name":"§cPrismarine Blade","lore":["§cPrismarine Blade","§7Click on this item in your inventory to","§7add it to your §9Museum§7!","","§7Reward: §b+2 SkyBlock XP","","§7§eRight click to search this item on the","§eAuction House!"]},{"sb_id":"NA","name":"§cHunter Knife","lore":["§cHunter Knife","§7Click on this item in your inventory to","§7add it to your §9Museum§7!","","§7Reward: §b+2 SkyBlock XP"]},null,null,{"sb_id":"NA","name":"§cUndead Bow","lore":["§cUndead Bow","§7Click on this item in your inventory to","§7add it to your §9Museum§7!","","§7Donating a §5Super Undead Bow §7will","§7count as donating this item.","","§7Reward: §b+2 SkyBlock XP","","§7§eRight click to search this item on the","§eAuction House!"]},{"sb_id":"CRYPT_DREADLORD_SWORD","name":"§9Odd Dreadlord Sword","lore":["§9Odd Dreadlord Sword","§7Gear Score: §d333 §8(804)","§7Damage: §c+84 §8(+252)","§7Strength: §c+38 §8(+114)","§7Crit Chance: §c+15% §9(+15%) §8(+15.6%)","§7Crit Damage: §c+65% §9(+15%) §8(+195%)","§7Intelligence: §a+122 §9(-18) §8(+366)","","§9Critical V§9, §9Experience III§9, §9First Strike IV","§9Giant Killer V§9, §9Life Steal III§9, §9Looting III","§9Luck V§9, §9Scavenger V§9, §9Sharpness V","§9Vampirism V","","§6Ability: Dreadlord  §e§lRIGHT CLICK","§7Shoot a skull that deals §a2,033.4§7","§7damage.","§8Mana Cost: §340","","§8§l* §8Co-op Soulbound §8§l*","§9§lRARE DUNGEON SWORD","§8§m §8§m §8§m §8§m §8§m §8§m §8§m §8§m §8§m §8§m §8§m §8§m §8§m §8§m §8§m §8§m §8§m §8§m §8§m §8§m §8§m §8§m §8§m §8§m §8§m ","§7Donated: §bOct 28, 2024","§7Created: §aOct 28, 2024","§7Clean Value: §66,999 Coins","§7Reward: §b+2 SkyBlock XP §a✔","","§9Atrium Slot #14","","§eClick to retrieve item!"]},{"sb_id":"NA","name":"§cSniper Bow","lore":["§cSniper Bow","§7Click on this item in your inventory to","§7add it to your §9Museum§7!","","§7Reward: §b+2 SkyBlock XP","","§7§eRight click to search this item on the","§eAuction House!"]},{"sb_id":"NA","name":"§cRecluse Fang","lore":["§cRecluse Fang","§7Click on this item in your inventory to","§7add it to your §9Museum§7!","","§7Reward: §b+2 SkyBlock XP","","§7§eRight click to search this item on the","§eAuction House!"]},{"sb_id":"NA","name":"§cStarlight Wand","lore":["§cStarlight Wand","§7Click on this item in your inventory to","§7add it to your §9Museum§7!","","§7Reward: §b+2 SkyBlock XP","","§7§eRight click to search this item on the","§eAuction House!"]},{"sb_id":"NA","name":"§cSuper Cleaver","lore":["§cSuper Cleaver","§7Click on this item in your inventory to","§7add it to your §9Museum§7!","","§7Donating a §5Hyper Cleaver §7will count","§7as donating this item.","","§7Reward: §b+2 SkyBlock XP","","§7§eRight click to search this item on the","§eAuction House!"]},{"sb_id":"NA","name":"§cTribal Spear","lore":["§cTribal Spear","§7Click on this item in your inventory to","§7add it to your §9Museum§7!","","§7Reward: §b+2 SkyBlock XP","","§7§eRight click to search this item on the","§eAuction House!"]},null,null,{"sb_id":"NA","name":"§cHyper Cleaver","lore":["§cHyper Cleaver","§7Click on this item in your inventory to","§7add it to your §9Museum§7!","","§7Donating a §5Giant Cleaver §7will count","§7as donating this item.","","§7Reward: §b+2 SkyBlock XP","","§7§eRight click to search this item on the","§eAuction House!"]},{"sb_id":"NA","name":"§cSuper Undead Bow","lore":["§cSuper Undead Bow","§7Click on this item in your inventory to","§7add it to your §9Museum§7!","","§7Donating a §5Death Bow §7will count as","§7donating this item.","","§7Reward: §b+2 SkyBlock XP","","§7§eRight click to search this item on the","§eAuction House!"]},{"sb_id":"NA","name":"§cArack","lore":["§cArack","§7Click on this item in your inventory to","§7add it to your §9Museum§7!","","§7Reward: §b+2 SkyBlock XP","","§7§eRight click to search this item on the","§eAuction House!"]},{"sb_id":"FLAMING_SWORD","name":"§aFlaming Sword","lore":["§aFlaming Sword","§7Damage: §c+50","§7Strength: §c+20","","§7Ignites enemies for §a3s§7.","","§7§8This item can be reforged!","§8§l* §8Co-op Soulbound §8§l*","§a§lUNCOMMON SWORD","§8§m §8§m §8§m §8§m §8§m §8§m §8§m §8§m §8§m §8§m §8§m §8§m §8§m §8§m §8§m §8§m §8§m §8§m §8§m §8§m §8§m §8§m §8§m §8§m §8§m ","§7Donated: §bOct 28, 2024","§7Created: §aSep 28, 2019","§7Clean Value: §6100,000 Coins","§7Reward: §b+3 SkyBlock XP §a✔","","§9Weapons Wing Slot #8","","§eClick to retrieve item!"]},{"sb_id":"NA","name":"§cDecent Bow","lore":["§cDecent Bow","§7Click on this item in your inventory to","§7add it to your §9Museum§7!","","§7Reward: §b+3 SkyBlock XP","","§7§eRight click to search this item on the","§eAuction House!"]},{"sb_id":"NA","name":"§cVoidwalker Katana","lore":["§cVoidwalker Katana","§7Click on this item in your inventory to","§7add it to your §9Museum§7!","","§7Donating a §9Voidedge Katana §7will count","§7as donating this item.","","§7Reward: §b+3 SkyBlock XP","","§7§eRight click to search this item on the","§eAuction House!"]},{"sb_id":"NA","name":"§cSavanna Bow","lore":["§cSavanna Bow","§7Click on this item in your inventory to","§7add it to your §9Museum§7!","","§7Reward: §b+3 SkyBlock XP","","§7§eRight click to search this item on the","§eAuction House!"]}]]}