{
    "Players In Range Display": {
        "x": 0.0,
        "y": 0.0
    },
    "Necron Phase Timer": {
        "x": 0.0,
        "y": 0.0
    },
    "Soulflow Display": {
        "x": 0.65,
        "y": 0.85
    },
    "Endstone Protector Spawn Timer": {
        "x": 0.0,
        "y": 0.0
    },
    "Container Sell Value": {
        "x": 0.258,
        "y": 0.283
    },
    "Livid HP": {
        "x": 0.0046875,
        "y": 0.4171103
    },
    "Stacking Enchant Display": {
        "x": 0.65,
        "y": 0.85
    },
    "Placed Summoning Eye Display": {
        "x": 0.0,
        "y": 0.0
    },
    "Rain Timer": {
        "x": 0.0,
        "y": 0.0
    },
    "Dungeon Timer": {
        "x": 0.0,
        "y": 0.0
    },
    "Seraph Display": {
        "x": 0.0,
        "y": 0.0
    },
    "Trophy Fish Display": {
        "x": 0.0,
        "y": 0.0
    },
    "Hidden Jerry Timer": {
        "x": 0.0,
        "y": 0.0
    },
    "Wither Shield Display": {
        "x": 0.671875,
        "y": 0.98022807
    },
    "Dungeon Map": {
        "x": 0.0036458333,
        "y": 0.0114068445,
        "scale": 0.9841968
    },
    "Spirit Bear Spawn Timer": {
        "x": 0.05,
        "y": 0.4
    },
    "Show Arachne HP": {
        "x": 0.0,
        "y": 0.0
    },
    "Dungeon Crypts Counter": {
        "x": 0.0,
        "y": 0.0,
        "scale": 2.0
    },
    "Sadan Phase Timer": {
        "x": 0.0,
        "y": 0.0
    },
    "Guardian Respawn Timer": {
        "x": 0.0,
        "y": 0.0
    },
    "Dungeon Secret Display": {
        "x": 0.05,
        "y": 0.4
    },
    "Kuudra Chest Profit": {
        "x": 0.0,
        "y": 0.0
    },
    "Dungeon Chest Profit": {
        "x": 0.0,
        "y": 0.0
    },
    "Dungeon Score Estimate": {
        "x": 0.0046875,
        "y": 0.44296578
    },
    "Slayer Armor Display": {
        "x": 0.0,
        "y": 0.0
    },
    "Totem Display": {
        "x": 0.0,
        "y": 0.0
    },
    "Mayor Jerry Tracker": {
        "x": 0.0,
        "y": 0.0
    },
    "Show Giant HP": {
        "x": 0.0,
        "y": 0.0
    },
    "Quiver Display": {
        "x": 0.05,
        "y": 0.4
    },
    "Mayor Jerry Perk Display": {
        "x": 0.0,
        "y": 0.0
    },
    "Slayer Display": {
        "x": 0.0,
        "y": 0.0
    },
    "Jamcat": {
        "x": 0.0,
        "y": 0.0
    },
    "Visitor Offer Helper": {
        "x": 0.258,
        "y": 0.283
    },
    "Selected Arrow Display": {
        "x": 0.82604164,
        "y": 0.33859316
    },
    "Spam Gui": {
        "x": 0.65,
        "y": 0.925
    },
    "Crystal Hollows Map": {
        "x": 0.003125,
        "y": 0.011396065,
        "scale": 2.766129
    },
    "Mythological Tracker": {
        "x": 0.0,
        "y": 0.0
    },
    "World Age Display": {
        "x": 0.0,
        "y": 0.0
    },
    "Item Cooldown Display": {
        "x": 0.48385417,
        "y": 0.25760457
    },
    "Ping Display": {
        "x": 0.9505208,
        "y": 0.18536122
    }
}